{"HotelID":49,"HotelName":"Park Grand London Hyde Park","HotelAddress":"78 82 Westbourne Terrace Westminster Borough London W2 6QA United Kingdom","Country":"United Kingdom","Phone":"0800 019 4066","OriginalHotelName":"Park Grand London Hyde Park","GoogleAddress":["78-82 Westbourne Terrace","London W2 6QA","United Kingdom"],"Latitude":"51.5157316","Longitude":"-0.1802179","gPlusPlaceId":"113236458045214157712","NearestAirportID":"EGLC"}
{"HotelID":176,"HotelName":"Les Jardins De La Villa Spa","HotelAddress":"5 Rue Belidor 17th arr 75017 Paris France","Country":"France","OriginalHotelName":"Les Jardins De La Villa Spa","Latitude":"48.8801757","Longitude":"2.2859534","NearestAirportID":"LFPV"}
{"HotelID":380,"HotelName":"United Lodge Hotel and Apartments","HotelAddress":"368 370 Green Lanes London N4 1DA United Kingdom","Country":"United Kingdom","OriginalHotelName":"United Lodge Hotel and Apartments","Latitude":"51.5743549","Longitude":"-0.0977567","NearestAirportID":"GB-0527"}
{"HotelID":520,"HotelName":"Hotel Marignan Champs Elys es","HotelAddress":"12 rue de Marignan 8th arr 75008 Paris France","Country":"France","OriginalHotelName":"Hotel Marignan Champs Elys es","Latitude":"48.8685093","Longitude":"2.3067895","NearestAirportID":"LFPV"}
{"HotelID":629,"HotelName":"Hotel de Nell","HotelAddress":"7 9 rue du Conservatoire 9th arr 75009 Paris France","Country":"France","Phone":"01 44 83 83 60","OriginalHotelName":"Hotel de Nell","GoogleAddress":["7-9 Rue du Conservatoire","75009 Paris","France"],"Latitude":"48.8732788","Longitude":"2.3466576","gPlusPlaceId":"108565580581349699413","NearestAirportID":"LFPB"}
{"HotelID":672,"HotelName":"Hotel Malte Astotel","HotelAddress":"63 rue de Richelieu 2nd arr 75002 Paris France","Country":"France","OriginalHotelName":"Hotel Malte Astotel","Latitude":"48.8672474","Longitude":"2.33738","NearestAirportID":"LFPB"}
{"HotelID":736,"HotelName":"Grange Beauchamp Hotel","HotelAddress":"24 27 Bedford Place Bloomsbury Camden London WC1B 5JH United Kingdom","Country":"United Kingdom","OriginalHotelName":"Grange Beauchamp Hotel","Latitude":"51.5203266","Longitude":"-0.1245891","NearestAirportID":"EGLC"}
{"HotelID":791,"HotelName":"H tel Cristal Champs Elys es","HotelAddress":"9 Rue de Washington 8th arr 75008 Paris France","Country":"France","OriginalHotelName":"H tel Cristal Champs Elys es","Latitude":"48.8726814","Longitude":"2.3020866","NearestAirportID":"LFPV"}
{"HotelID":1041,"HotelName":"Hotel Reding","HotelAddress":"Bergara 2 4 Eixample 08002 Barcelona Spain","Country":"Spain","Phone":"934 12 10 97","OriginalHotelName":"Hotel Regina","GoogleAddress":["Carrer de Gravina, 5-7","08001 Barcelona","Spain"],"Latitude":"41.3858891","Longitude":"2.1681652","gPlusPlaceId":"112494992755051122075","NearestAirportID":"LEBL"}
{"HotelID":1075,"HotelName":"Goralska R sidences H tel Paris Bastille","HotelAddress":"7 Boulevard Bourdon 4th arr 75004 Paris France","Country":"France","OriginalHotelName":"Goralska R sidences H tel Paris Bastille","Latitude":"48.8482842","Longitude":"2.3657251","NearestAirportID":"LFPO"}
{"HotelID":1076,"HotelName":"Mercure Paris Gobelins Place d Italie","HotelAddress":"8 bis Avenue de la Soeur Rosalie 13th arr 75013 Paris France","Country":"France","OriginalHotelName":"Mercure Paris Gobelins Place d Italie","Latitude":"48.8321231","Longitude":"2.3536172","NearestAirportID":"LFPO"}
{"HotelID":1111,"HotelName":"Hotel Boutique Duomo","HotelAddress":"Via Mac Mahon 45 Sempione 20155 Milan Italy","Country":"Italy","OriginalHotelName":"Hotel Boutique Duomo","Latitude":"45.4909585","Longitude":"9.1614268","NearestAirportID":"LIMB"}
{"HotelID":1116,"HotelName":"Lyric H tel Paris","HotelAddress":"2 rue de Gramont 2nd arr 75002 Paris France","Country":"France","OriginalHotelName":"Lyric H tel Paris","Latitude":"48.8690126","Longitude":"2.3368708","NearestAirportID":"LFPB"}
{"HotelID":1287,"HotelName":"Hotel Barcelona Universal","HotelAddress":"Avinguda Paral lel 76 78 Ciutat Vella 08001 Barcelona Spain","Country":"Spain","Phone":"935 67 74 47","OriginalHotelName":"Hotel Barcelona Universal","GoogleAddress":["Avinguda del Paraŀlel, 76-80","08001 Barcelona","Spain"],"Latitude":"41.375237","Longitude":"2.1684058","gPlusPlaceId":"114243081498579221906","NearestAirportID":"LEBL"}
{"HotelID":1462,"HotelName":"NH Milano Machiavelli","HotelAddress":"Via Lazzaretto 5 Central Station 20124 Milan Italy","Country":"Italy","OriginalHotelName":"NH Milano Machiavelli","Latitude":"45.4776167","Longitude":"9.2016244","NearestAirportID":"LIML"}
